Metadata-Version: 2.1
Name: arseeding
Version: 0.0.6
Summary: Python sdk for arseeding
Home-page: https://github.com/everFinance/arseeding.py
Download-URL: https://github.com/everFinance/arseeding.py/archive/refs/tags/v0.0.6.tar.gz
Author: xiaojay
Author-email: xiaojay@gmail.com
License: MIT
Classifier: Programming Language :: Python :: 3
Classifier: Programming Language :: Python :: 2
Classifier: License :: OSI Approved :: MIT License
Classifier: Operating System :: OS Independent
License-File: LICENSE
